composite/__init__.py
composite/const.py
composite/documents.py
composite/exceptions.py
composite/fields.py
composite/version.py
composite/builders/__init__.py
composite/builders/base.py
composite/builders/python.py
composite/builders/xml.py
composite/visitors/__init__.py
composite/visitors/base.py
composite/visitors/builders.py
composite/visitors/parsers.py
python_composite-0.1.0.dist-info/DESCRIPTION.rst
python_composite-0.1.0.dist-info/METADATA
python_composite-0.1.0.dist-info/RECORD
python_composite-0.1.0.dist-info/WHEEL
python_composite-0.1.0.dist-info/metadata.json
python_composite-0.1.0.dist-info/top_level.txt
