Metadata-Version: 2.0
Name: python-composite
Version: 0.1.0
Summary: Declarative work with nested documents (JSON, XML, etc)
Home-page: UNKNOWN
Author: Nickolas Fox <tarvitz@blacklibrary.ru>
Author-email: tarvitz@blacklibrary.ru
License: MIT license
Download-URL: https://github.com/tarvitz/composite/archive/master.zip
Platform: OS Independent
Classifier: Development Status :: 4 - Beta
Classifier: Environment :: Console
Classifier: Intended Audience :: Developers
Classifier: License :: OSI Approved :: MIT License
Classifier: Operating System :: OS Independent
Classifier: Programming Language :: Python
Classifier: Natural Language :: English
Classifier: Topic :: Utilities
Classifier: Programming Language :: Python :: 2.7
Classifier: Programming Language :: Python :: 3
Classifier: Programming Language :: Python :: 3.3
Classifier: Programming Language :: Python :: 3.4
Classifier: Programming Language :: Python :: 3.5
Classifier: Programming Language :: Python :: 3.6
Requires-Dist: lxml
Requires-Dist: six
